odoo/addons/hr_timesheet_task_domain/README.rst
odoo/addons/hr_timesheet_task_domain/__init__.py
odoo/addons/hr_timesheet_task_domain/__manifest__.py
odoo/addons/hr_timesheet_task_domain/i18n/de.po
odoo/addons/hr_timesheet_task_domain/i18n/es.po
odoo/addons/hr_timesheet_task_domain/i18n/hr_timesheet_task_domain.pot
odoo/addons/hr_timesheet_task_domain/i18n/it.po
odoo/addons/hr_timesheet_task_domain/models/__init__.py
odoo/addons/hr_timesheet_task_domain/models/account_analytic_line.py
odoo/addons/hr_timesheet_task_domain/readme/CONTRIBUTORS.rst
odoo/addons/hr_timesheet_task_domain/readme/DESCRIPTION.rst
odoo/addons/hr_timesheet_task_domain/static/description/icon.png
odoo/addons/hr_timesheet_task_domain/static/description/index.html
odoo/addons/hr_timesheet_task_domain/tests/__init__.py
odoo/addons/hr_timesheet_task_domain/tests/test_hr_timesheet_task_domain.py
odoo13_addon_hr_timesheet_task_domain-13.0.1.0.1.dev9.dist-info/METADATA
odoo13_addon_hr_timesheet_task_domain-13.0.1.0.1.dev9.dist-info/WHEEL
odoo13_addon_hr_timesheet_task_domain-13.0.1.0.1.dev9.dist-info/top_level.txt
odoo13_addon_hr_timesheet_task_domain-13.0.1.0.1.dev9.dist-info/RECORD
